[
  {
    "Browser":"Chrome",
    "Percentage":38.67
  },
  {
    "Browser":"IE",
    "Percentage":29.1
  },
  {
    "Browser":"Firefox",
    "Percentage":20.77
  },
  {
    "Browser":"Safari",
    "Percentage":8.2
  },
  {
    "Browser":"Opera",
    "Percentage":1.23
  },
  {
    "Browser":"Android",
    "Percentage":0.72
  },
  {
    "Browser":"Yandex Browser",
    "Percentage":0.18
  },
  {
    "Browser":"Maxthon",
    "Percentage":0.16
  },
  {
    "Browser":"Sogou Explorer",
    "Percentage":0.15
  },
  {
    "Browser":"Silk",
    "Percentage":0.14
  },
  {
    "Browser":"360 Safe Browser",
    "Percentage":0.14
  },
  {
    "Browser":"Sony PS3",
    "Percentage":0.12
  },
  {
    "Browser":"Chromium",
    "Percentage":0.07
  },
  {
    "Browser":"RockMelt",
    "Percentage":0.04
  },
  {
    "Browser":"BlackBerry",
    "Percentage":0.04
  },
  {
    "Browser":"Pale Moon",
    "Percentage":0.04
  },
  {
    "Browser":"QQ Browser",
    "Percentage":0.04
  },
  {
    "Browser":"Netscape",
    "Percentage":0.02
  },
  {
    "Browser":"SeaMonkey",
    "Percentage":0.02
  },
  {
    "Browser":"TheWorld",
    "Percentage":0.02
  },
  {
    "Browser":"Tencent Traveler",
    "Percentage":0.02
  },
  {
    "Browser":"Iron",
    "Percentage":0.01
  },
  {
    "Browser":"AppleWebKit",
    "Percentage":0.01
  },
  {
    "Browser":"Phantom",
    "Percentage":0.01
  },
  {
    "Browser":"Mozilla",
    "Percentage":0.01
  },
  {
    "Browser":"webOS Browser",
    "Percentage":0.01
  },
  {
    "Browser":"UC Browser",
    "Percentage":0.01
  },
  {
    "Browser":"Kindle",
    "Percentage":0.01
  },
  {
    "Browser":"Puffin",
    "Percentage":0.01
  },
  {
    "Browser":"Unknown",
    "Percentage":0.01
  },
  {
    "Browser":"Camino",
    "Percentage":0.01
  },
  {
    "Browser":"Iceweasel",
    "Percentage":0.01
  },
  {
    "Browser":"Flock",
    "Percentage":0.01
  },
  {
    "Browser":"Comodo Dragon",
    "Percentage":0
  },
  {
    "Browser":"CoRom+",
    "Percentage":0
  },
  {
    "Browser":"Lunascape",
    "Percentage":0
  },
  {
    "Browser":"Sleipnir",
    "Percentage":0
  },
  {
    "Browser":"Beamrise",
    "Percentage":0
  },
  {
    "Browser":"Minefield",
    "Percentage":0
  },
  {
    "Browser":"Midori",
    "Percentage":0
  },
  {
    "Browser":"AOL",
    "Percentage":0
  },
  {
    "Browser":"K-Meleon",
    "Percentage":0
  },
  {
    "Browser":"Windows Media Player",
    "Percentage":0
  },
  {
    "Browser":"Epiphany",
    "Percentage":0
  },
  {
    "Browser":"Anonymouse",
    "Percentage":0
  },
  {
    "Browser":"Konqueror",
    "Percentage":0
  },
  {
    "Browser":"Fake IE",
    "Percentage":0
  },
  {
    "Browser":"OmniWeb",
    "Percentage":0
  },
  {
    "Browser":"rekonq",
    "Percentage":0
  },
  {
    "Browser":"Nokia",
    "Percentage":0
  },
  {
    "Browser":"WebTV/MSNTV",
    "Percentage":0
  },
  {
    "Browser":"MS OPD",
    "Percentage":0
  },
  {
    "Browser":"FrontPage",
    "Percentage":0
  },
  {
    "Browser":"iPod Touch",
    "Percentage":0
  },
  {
    "Browser":"NetFront",
    "Percentage":0
  },
  {
    "Browser":"Links",
    "Percentage":0
  },
  {
    "Browser":"Obigo",
    "Percentage":0
  },
  {
    "Browser":"NetSurf",
    "Percentage":0
  },
  {
    "Browser":"Dolphin",
    "Percentage":0
  },
  {
    "Browser":"WebPositive",
    "Percentage":0
  },
  {
    "Browser":"Galeon",
    "Percentage":0
  },
  {
    "Browser":"JoeDog",
    "Percentage":0
  },
  {
    "Browser":"Microsoft URL Control",
    "Percentage":0
  },
  {
    "Browser":"Webaroo",
    "Percentage":0
  },
  {
    "Browser":"Vienna",
    "Percentage":0
  },
  {
    "Browser":"Skyfire",
    "Percentage":0
  },
  {
    "Browser":"Lynx",
    "Percentage":0
  },
  {
    "Browser":"Baidu Explorer",
    "Percentage":0
  },
  {
    "Browser":"Firebird",
    "Percentage":0
  },
  {
    "Browser":"Amiga",
    "Percentage":0
  },
  {
    "Browser":"Thunderbird",
    "Percentage":0
  },
  {
    "Browser":"Dillo",
    "Percentage":0
  },
  {
    "Browser":"w3m",
    "Percentage":0
  },
  {
    "Browser":"Microsoft-WebDAV",
    "Percentage":0
  },
  {
    "Browser":"Openwave Mobile Browser",
    "Percentage":0
  },
  {
    "Browser":"Squid",
    "Percentage":0
  },
  {
    "Browser":"iBrowser",
    "Percentage":0
  },
  {
    "Browser":"Charlotte",
    "Percentage":0
  },
  {
    "Browser":"Anonymous",
    "Percentage":0
  },
  {
    "Browser":"IceCat",
    "Percentage":0
  },
  {
    "Browser":"Chimera",
    "Percentage":0
  },
  {
    "Browser":"Avant Browser",
    "Percentage":0
  },
  {
    "Browser":"ELinks",
    "Percentage":0
  },
  {
    "Browser":"iTunes",
    "Percentage":0
  },
  {
    "Browser":"iPhone",
    "Percentage":0
  },
  {
    "Browser":"Microsoft Office Existence Discovery",
    "Percentage":0
  },
  {
    "Browser":"Proxomitron",
    "Percentage":0
  },
  {
    "Browser":"iCab",
    "Percentage":0
  },
  {
    "Browser":"ibisBrowser",
    "Percentage":0
  },
  {
    "Browser":"Apple-PubSub",
    "Percentage":0
  },
  {
    "Browser":"Sundance",
    "Percentage":0
  },
  {
    "Browser":"Windows-Media-Player",
    "Percentage":0
  },
  {
    "Browser":"Shiira",
    "Percentage":0
  },
  {
    "Browser":"SmallProxy",
    "Percentage":0
  },
  {
    "Browser":"Emacs/W3",
    "Percentage":0
  },
  {
    "Browser":"BrowseX",
    "Percentage":0
  },
  {
    "Browser":"VLC",
    "Percentage":0
  },
  {
    "Browser":"NetPositive",
    "Percentage":0
  },
  {
    "Browser":"Twitturly",
    "Percentage":0
  },
  {
    "Browser":"Coast",
    "Percentage":0
  },
  {
    "Browser":"General Crawlers",
    "Percentage":0
  },
  {
    "Browser":"SaferSurf",
    "Percentage":0
  },
  {
    "Browser":"NetFront Life",
    "Percentage":0
  },
  {
    "Browser":"LG",
    "Percentage":0
  },
  {
    "Browser":"IEMobile",
    "Percentage":0
  },
  {
    "Browser":"CE-Preload",
    "Percentage":0
  },
  {
    "Browser":"HP Secure Web Browser",
    "Percentage":0
  },
  {
    "Browser":"ogeb browser",
    "Percentage":0
  },
  {
    "Browser":"Privoxy",
    "Percentage":0
  },
  {
    "Browser":"Amaya",
    "Percentage":0
  },
  {
    "Browser":"Netbox",
    "Percentage":0
  },
  {
    "Browser":"Microsoft Excel",
    "Percentage":0
  },
  {
    "Browser":"Microsoft Visio",
    "Percentage":0
  },
  {
    "Browser":"BITS",
    "Percentage":0
  },
  {
    "Browser":"IBrowse",
    "Percentage":0
  },
  {
    "Browser":"1st ZipCommander",
    "Percentage":0
  },
  {
    "Browser":"Anonymizied",
    "Percentage":0
  },
  {
    "Browser":"Microsoft",
    "Percentage":0
  },
  {
    "Browser":"vobsub",
    "Percentage":0
  },
  {
    "Browser":"Zune",
    "Percentage":0
  },
  {
    "Browser":"SonyEricsson",
    "Percentage":0
  },
  {
    "Browser":"Bolt",
    "Percentage":0
  },
  {
    "Browser":"WinAmp",
    "Percentage":0
  },
  {
    "Browser":"Enigma Browser",
    "Percentage":0
  },
  {
    "Browser":"MS IPPPD",
    "Percentage":0
  },
  {
    "Browser":"RMA",
    "Percentage":0
  },
  {
    "Browser":"MFHttpScan",
    "Percentage":0
  },
  {
    "Browser":"MS IPP DAV",
    "Percentage":0
  },
  {
    "Browser":"Anonymizer",
    "Percentage":0
  },
  {
    "Browser":"SlimBrowser",
    "Percentage":0
  },
  {
    "Browser":"Arora",
    "Percentage":0
  },
  {
    "Browser":"RealPlayer",
    "Percentage":0
  },
  {
    "Browser":"QuickTime",
    "Percentage":0
  },
  {
    "Browser":"Mosaic",
    "Percentage":0
  },
  {
    "Browser":"SEMC Browser",
    "Percentage":0
  },
  {
    "Browser":"MS Proxy",
    "Percentage":0
  },
  {
    "Browser":"Ace Explorer",
    "Percentage":0
  },
  {
    "Browser":"MS IPP",
    "Percentage":0
  },
  {
    "Browser":"Samsung",
    "Percentage":0
  },
  {
    "Browser":"Pocket PC",
    "Percentage":0
  },
  {
    "Browser":"Google Desktop",
    "Percentage":0
  },
  {
    "Browser":"GreenBrowser",
    "Percentage":0
  },
  {
    "Browser":"Google",
    "Percentage":0
  },
  {
    "Browser":"WordPress",
    "Percentage":0
  },
  {
    "Browser":"Wipeout Pure",
    "Percentage":0
  },
  {
    "Browser":"Escape",
    "Percentage":0
  },
  {
    "Browser":"Websense",
    "Percentage":0
  },
  {
    "Browser":"Rippers",
    "Percentage":0
  },
  {
    "Browser":"Blazer",
    "Percentage":0
  },
  {
    "Browser":"Yahoo! My Browser",
    "Percentage":0
  },
  {
    "Browser":"fantomas multiBlocker browser",
    "Percentage":0
  },
  {
    "Browser":"fantomas fantomCrew Browser",
    "Percentage":0
  },
  {
    "Browser":"MFC Foundation Class Library",
    "Percentage":0
  }
]